{
  "gitSyncId": "6776409599a03b6e785aa1c3_26d9ae4b-0af0-4bf9-b620-c7fbe2f4fc72",
  "id": "home_existCarousel",
  "pluginId": "postgres-plugin",
  "pluginType": "DB",
  "unpublishedAction": {
    "actionConfiguration": {
      "body": "SELECT count(1) \nFROM carousel \nWHERE owner_id = {{appsmith.store.growing.id}} AND name = {{this.params.name}} AND delete_flag = false;",
      "encodeParamsToggle": true,
      "paginationType": "NONE",
      "pluginSpecifiedTemplates": [
        {
          "value": true
        }
      ],
      "timeoutInMillisecond": 10000
    },
    "confirmBeforeExecute": false,
    "datasource": {
      "id": "本地数据库",
      "isAutoGenerated": false,
      "name": "本地数据库",
      "pluginId": "postgres-plugin"
    },
    "dynamicBindingPathList": [
      {
        "key": "body"
      }
    ],
    "executeOnLoad": false,
    "name": "existCarousel",
    "pageId": "home",
    "userSetOnLoad": false
  }
}